ocrd_jdeskew/__init__.py
ocrd_jdeskew/deskew.py
ocrd_jdeskew/ocrd-tool.json
ocrd_jdeskew-0.0.2.dist-info/LICENSE
ocrd_jdeskew-0.0.2.dist-info/METADATA
ocrd_jdeskew-0.0.2.dist-info/WHEEL
ocrd_jdeskew-0.0.2.dist-info/entry_points.txt
ocrd_jdeskew-0.0.2.dist-info/top_level.txt
ocrd_jdeskew-0.0.2.dist-info/RECORD
