Metadata-Version: 2.1
Name: ocrd-jdeskew
Version: 0.0.2
Summary: OCR-D wrapper for Document Image Skew Estimation using Adaptive Radial Projection
Author-email: Robert Sachunsky <sachunsky@informatik.uni-leipzig.de>
License: MIT License
Project-URL: Repository, https://github.com/bertsky/ocrd_jdeskew
License-File: LICENSE
Requires-Dist: jdeskew
Requires-Dist: ocrd
